{
  "name": "Athlétisme",
  "type": "skill",
  "img": "systems/arlenor/assets/images_filled/skills/./other.png",
  "system": {
    "description": "Bonus +1D6 pour toute action de course, lancer, saut, nage et acrobatie.",
    "skillType": "OTHER"
  },
  "effects": [],
  "folder": "x0hf12DV28jV5Twm",
  "ownership": {
    "default": 0
  },
  "flags": {},
  "_stats": {
    "systemId": "arlenor",
    "systemVersion": "1.2.0",
    "coreVersion": "11.315",
    "createdTime": null,
    "modifiedTime": null,
    "lastModifiedBy": null
  },
  "_id": "Qcbv5Jo1RuAmzC8K",
  "sort": 0,
  "_key": "!items!Qcbv5Jo1RuAmzC8K"
}