{
  "name": "Mélodie Apaisante",
  "type": "power",
  "img": "systems/arlenor/assets/images_filled/powers/heal.png",
  "system": {
    "description": "Joue une mélodie apaisante qui réduit les tensions et les blessures des alliés dans la zone, annulant les malus engendrés par elles.",
    "powerType": "EVO",
    "speciality": "BARDE",
    "category": "CHANELING",
    "family": "HEAL",
    "rank": "C",
    "duration": "1",
    "range": "3"
  },
  "effects": [],
  "folder": "cRbfcX0BTimMVFj9",
  "ownership": {
    "default": 0
  },
  "flags": {},
  "_stats": {
    "systemId": "arlenor",
    "systemVersion": "1.2.0",
    "coreVersion": "11.315",
    "createdTime": null,
    "modifiedTime": null,
    "lastModifiedBy": null
  },
  "_id": "h5Eion2uGTTIgfat",
  "sort": 0,
  "_key": "!items!h5Eion2uGTTIgfat"
}